{"commitInfo":{"timestamp":1778798190632,"userId":"70488675478155","userName":"supreethbmohan@icloud.com","operation":"WRITE","operationParameters":{"mode":"Overwrite","statsOnLoad":false,"partitionBy":"[\"location\"]"},"notebook":{"notebookId":"3106716418963635"},"queryHistoryStatementId":"d625ed93-c347-441a-918f-e7602b4d2c61","clusterId":"0514-220722-9khd7ja-v2n","isolationLevel":"WriteSerializable","isBlindAppend":false,"operationMetrics":{"numFiles":"2","numRemovedFiles":"0","numRemovedBytes":"0","numDeletionVectorsRemoved":"0","numOutputRows":"2","numOutputBytes":"2222"},"tags":{"noRowsCopied":"true","restoresDeletedRows":"false"},"engineInfo":"Databricks-Runtime/18.1.x-aarch64-photon-scala2.13","txnId":"67a675e7-ee67-44b0-a19b-3a3dac89f30d"}}
{"metaData":{"id":"b5d0ad54-129d-4cde-ab46-7b857490daff","format":{"provider":"parquet","options":{}},"schemaString":"{\"type\":\"struct\",\"fields\":[{\"name\":\"customer_id\",\"type\":\"integer\",\"nullable\":true,\"metadata\":{}},{\"name\":\"customer_name\",\"type\":\"string\",\"nullable\":true,\"metadata\":{}},{\"name\":\"location\",\"type\":\"string\",\"nullable\":true,\"metadata\":{}}]}","partitionColumns":["location"],"configuration":{"delta.enableDeletionVectors":"true"},"createdTime":1778798187494}}
{"protocol":{"minReaderVersion":3,"minWriterVersion":7,"readerFeatures":["deletionVectors"],"writerFeatures":["deletionVectors","appendOnly","invariants"]}}
{"add":{"path":"location=Colorado/part-00000-8eefa6ab-4e8d-4260-984b-614d34c053e0.c000.snappy.parquet","partitionValues":{"location":"Colorado"},"size":1122,"modificationTime":1778798189000,"dataChange":true,"stats":"{\"numRecords\":1,\"minValues\":{\"customer_id\":107,\"customer_name\":\"Grace\"},\"maxValues\":{\"customer_id\":107,\"customer_name\":\"Grace\"},\"nullCount\":{\"customer_id\":0,\"customer_name\":0},\"tightBounds\":true}","tags":{"INSERTION_TIME":"1778798189000000","MIN_INSERTION_TIME":"1778798189000000","MAX_INSERTION_TIME":"1778798189000000","OPTIMIZE_TARGET_SIZE":"268435456"}}}
{"add":{"path":"location=Utah/part-00001-a9967927-03a6-41ab-94ed-b116105be66f.c000.snappy.parquet","partitionValues":{"location":"Utah"},"size":1100,"modificationTime":1778798189000,"dataChange":true,"stats":"{\"numRecords\":1,\"minValues\":{\"customer_id\":108,\"customer_name\":\"Henry\"},\"maxValues\":{\"customer_id\":108,\"customer_name\":\"Henry\"},\"nullCount\":{\"customer_id\":0,\"customer_name\":0},\"tightBounds\":true}","tags":{"INSERTION_TIME":"1778798189000001","MIN_INSERTION_TIME":"1778798189000001","MAX_INSERTION_TIME":"1778798189000001","OPTIMIZE_TARGET_SIZE":"268435456"}}}
